{
    "assets": [],
    "categories": [],
    "fields": {
        "Default": {
            "body": {
                "name": "Body",
                "context": "global",
                "instructions": null,
                "translatable": 1,
                "type": "RichText",
                "settings": {
                    "configFile": "Standard.json",
                    "columnType": "text"
                }
            },
            "tags": {
                "name": "Tags",
                "context": "global",
                "instructions": null,
                "translatable": 0,
                "type": "Tags",
                "settings": {
                    "source": "taggroup:1"
                }
            }
        }
    },
    "globals": [],
    "sections": {
        "about": {
            "name": "About",
            "type": "single",
            "hasUrls": 1,
            "template": "about",
            "maxLevels": null,
            "enableVersioning": 1,
            "locales": {
                "en_us": {
                    "enabledByDefault": 0,
                    "urlFormat": "about",
                    "nestedUrlFormat": null
                }
            },
            "entryTypes": {
                "about": {
                    "name": "About",
                    "hasTitleField": 0,
                    "titleLabel": null,
                    "titleFormat": "{section.name|raw}",
                    "fieldLayout": {
                        "fields": []
                    }
                }
            }
        },
        "contact": {
            "name": "Contact",
            "type": "single",
            "hasUrls": 1,
            "template": "contact",
            "maxLevels": null,
            "enableVersioning": 1,
            "locales": {
                "en_us": {
                    "enabledByDefault": 0,
                    "urlFormat": "contact",
                    "nestedUrlFormat": null
                }
            },
            "entryTypes": {
                "contact": {
                    "name": "Contact",
                    "hasTitleField": 0,
                    "titleLabel": null,
                    "titleFormat": "{section.name|raw}",
                    "fieldLayout": {
                        "fields": []
                    }
                }
            }
        },
        "donation": {
            "name": "Donation",
            "type": "single",
            "hasUrls": 1,
            "template": "donation",
            "maxLevels": null,
            "enableVersioning": 1,
            "locales": {
                "en_us": {
                    "enabledByDefault": 0,
                    "urlFormat": "donation",
                    "nestedUrlFormat": null
                }
            },
            "entryTypes": {
                "donation": {
                    "name": "Donation",
                    "hasTitleField": 0,
                    "titleLabel": null,
                    "titleFormat": "{section.name|raw}",
                    "fieldLayout": {
                        "fields": []
                    }
                }
            }
        },
        "events": {
            "name": "Events",
            "type": "single",
            "hasUrls": 1,
            "template": "events",
            "maxLevels": null,
            "enableVersioning": 1,
            "locales": {
                "en_us": {
                    "enabledByDefault": 0,
                    "urlFormat": "events",
                    "nestedUrlFormat": null
                }
            },
            "entryTypes": {
                "events": {
                    "name": "Events",
                    "hasTitleField": 0,
                    "titleLabel": null,
                    "titleFormat": "{section.name|raw}",
                    "fieldLayout": {
                        "fields": []
                    }
                }
            }
        },
        "faq": {
            "name": "FAQ",
            "type": "channel",
            "hasUrls": 1,
            "template": "faqTopics/_entry",
            "maxLevels": null,
            "enableVersioning": 1,
            "locales": {
                "en_us": {
                    "enabledByDefault": 0,
                    "urlFormat": "faq/{slug}",
                    "nestedUrlFormat": null
                }
            },
            "entryTypes": {
                "faq": {
                    "name": "FAQ",
                    "hasTitleField": 1,
                    "titleLabel": "Title",
                    "titleFormat": null,
                    "fieldLayout": {
                        "fields": []
                    }
                }
            }
        },
        "faqTopics": {
            "name": "FAQ Topics",
            "type": "single",
            "hasUrls": 1,
            "template": "faqTopics",
            "maxLevels": null,
            "enableVersioning": 1,
            "locales": {
                "en_us": {
                    "enabledByDefault": 0,
                    "urlFormat": "faq-topics",
                    "nestedUrlFormat": null
                }
            },
            "entryTypes": {
                "faqTopics": {
                    "name": "FAQ Topics",
                    "hasTitleField": 0,
                    "titleLabel": null,
                    "titleFormat": "{section.name|raw}",
                    "fieldLayout": {
                        "fields": []
                    }
                }
            }
        },
        "homepage": {
            "name": "Homepage",
            "type": "single",
            "hasUrls": 1,
            "template": "index",
            "maxLevels": null,
            "enableVersioning": 1,
            "locales": {
                "en_us": {
                    "enabledByDefault": 1,
                    "urlFormat": "__home__",
                    "nestedUrlFormat": null
                }
            },
            "entryTypes": {
                "homepage": {
                    "name": "Homepage",
                    "hasTitleField": 1,
                    "titleLabel": "Title",
                    "titleFormat": null,
                    "fieldLayout": {
                        "tabs": {
                            "Content": {
                                "body": 1
                            }
                        }
                    }
                }
            }
        },
        "jobDescription": {
            "name": "Job Description",
            "type": "channel",
            "hasUrls": 1,
            "template": "jobOpenings/_entry",
            "maxLevels": null,
            "enableVersioning": 1,
            "locales": {
                "en_us": {
                    "enabledByDefault": 0,
                    "urlFormat": "job-description/{slug}",
                    "nestedUrlFormat": null
                }
            },
            "entryTypes": {
                "jobDescription": {
                    "name": "Job Description",
                    "hasTitleField": 1,
                    "titleLabel": "Title",
                    "titleFormat": null,
                    "fieldLayout": {
                        "fields": []
                    }
                }
            }
        },
        "jobOpenings": {
            "name": "Job Openings",
            "type": "single",
            "hasUrls": 1,
            "template": "jobOpenings",
            "maxLevels": null,
            "enableVersioning": 1,
            "locales": {
                "en_us": {
                    "enabledByDefault": 0,
                    "urlFormat": "job-openings",
                    "nestedUrlFormat": null
                }
            },
            "entryTypes": {
                "jobOpenings": {
                    "name": "Job Openings",
                    "hasTitleField": 0,
                    "titleLabel": null,
                    "titleFormat": "{section.name|raw}",
                    "fieldLayout": {
                        "fields": []
                    }
                }
            }
        },
        "news": {
            "name": "News",
            "type": "single",
            "hasUrls": 1,
            "template": "news",
            "maxLevels": null,
            "enableVersioning": 1,
            "locales": {
                "en_us": {
                    "enabledByDefault": 0,
                    "urlFormat": "news",
                    "nestedUrlFormat": null
                }
            },
            "entryTypes": {
                "news": {
                    "name": "News",
                    "hasTitleField": 0,
                    "titleLabel": null,
                    "titleFormat": "{section.name|raw}",
                    "fieldLayout": {
                        "fields": []
                    }
                }
            }
        },
        "newsArticle": {
            "name": "News Article",
            "type": "channel",
            "hasUrls": 1,
            "template": "news/_entry",
            "maxLevels": null,
            "enableVersioning": 1,
            "locales": {
                "en_us": {
                    "enabledByDefault": 0,
                    "urlFormat": "news-article/{slug}",
                    "nestedUrlFormat": null
                }
            },
            "entryTypes": {
                "newsArticle": {
                    "name": "News Article",
                    "hasTitleField": 1,
                    "titleLabel": "Title",
                    "titleFormat": null,
                    "fieldLayout": {
                        "fields": []
                    }
                }
            }
        },
        "publications": {
            "name": "Publications",
            "type": "single",
            "hasUrls": 1,
            "template": "publications",
            "maxLevels": null,
            "enableVersioning": 1,
            "locales": {
                "en_us": {
                    "enabledByDefault": 0,
                    "urlFormat": "publications",
                    "nestedUrlFormat": null
                }
            },
            "entryTypes": {
                "publications": {
                    "name": "Publications",
                    "hasTitleField": 0,
                    "titleLabel": null,
                    "titleFormat": "{section.name|raw}",
                    "fieldLayout": {
                        "fields": []
                    }
                }
            }
        },
        "resources": {
            "name": "Resources",
            "type": "single",
            "hasUrls": 1,
            "template": "resources",
            "maxLevels": null,
            "enableVersioning": 1,
            "locales": {
                "en_us": {
                    "enabledByDefault": 0,
                    "urlFormat": "resources",
                    "nestedUrlFormat": null
                }
            },
            "entryTypes": {
                "resources": {
                    "name": "Resources",
                    "hasTitleField": 0,
                    "titleLabel": null,
                    "titleFormat": "{section.name|raw}",
                    "fieldLayout": {
                        "fields": []
                    }
                }
            }
        },
        "staff": {
            "name": "Staff",
            "type": "single",
            "hasUrls": 1,
            "template": "staff",
            "maxLevels": null,
            "enableVersioning": 1,
            "locales": {
                "en_us": {
                    "enabledByDefault": 0,
                    "urlFormat": "staff",
                    "nestedUrlFormat": null
                }
            },
            "entryTypes": {
                "staff": {
                    "name": "Staff",
                    "hasTitleField": 0,
                    "titleLabel": null,
                    "titleFormat": "{section.name|raw}",
                    "fieldLayout": {
                        "fields": []
                    }
                }
            }
        },
        "testing": {
            "name": "Testing",
            "type": "single",
            "hasUrls": 1,
            "template": "testing",
            "maxLevels": null,
            "enableVersioning": 1,
            "locales": {
                "en_us": {
                    "enabledByDefault": 0,
                    "urlFormat": "testing",
                    "nestedUrlFormat": null
                }
            },
            "entryTypes": {
                "testing": {
                    "name": "Testing",
                    "hasTitleField": 0,
                    "titleLabel": null,
                    "titleFormat": "{section.name|raw}",
                    "fieldLayout": {
                        "fields": []
                    }
                }
            }
        }
    },
    "tags": []
}
